tabfilepy/__init__.py
tabfilepy/fp_autocomplete.cmd
tabfilepy/fp_autocomplete.sh
tabfilepy-1.1.1.dist-info/licenses/LICENSE
tabfilepy-1.1.1.dist-info/METADATA
tabfilepy-1.1.1.dist-info/WHEEL
tabfilepy-1.1.1.dist-info/entry_points.txt
tabfilepy-1.1.1.dist-info/top_level.txt
tabfilepy-1.1.1.dist-info/RECORD
