Metadata-Version: 2.4
Name: tabfilepy
Version: 1.1.1
Summary: A simple Python (and associated cmd/bash) script which allows file directory tab auto-completions.
Author-email: Nyoman <nnyomandhipa@gmail.com>
License:                   GNU LESSER GENERAL PUBLIC LICENSE
Project-URL: Homepage, https://github.com/nelideven/tabfilepy
Requires-Python: >=3.7
License-File: LICENSE
Dynamic: license-file
